seadex/__init__.py
seadex/__main__.py
seadex/_backup.py
seadex/_entry.py
seadex/_enums.py
seadex/_exceptions.py
seadex/_torrent.py
seadex/_types.py
seadex/_utils.py
seadex/_version.py
seadex/py.typed
seadex/_cli/__init__.py
seadex/_cli/_backup.py
seadex/_cli/_entry.py
seadex/_cli/_torrent.py
seadex-0.7.2.dist-info/METADATA
seadex-0.7.2.dist-info/WHEEL
seadex-0.7.2.dist-info/entry_points.txt
seadex-0.7.2.dist-info/licenses/LICENSE
seadex-0.7.2.dist-info/RECORD
