Metadata-Version: 2.4
Name: seadex
Version: 0.7.2
Summary: Python wrapper for the SeaDex API.
Project-URL: Documentation, https://ravencentric.cc/seadex/
Project-URL: Repository, https://github.com/Ravencentric/seadex
Author-email: Ravencentric <me@ravencentric.cc>
License-Expression: MIT
License-File: LICENSE
Keywords: anime,releases.moe,seadex
Classifier: Operating System :: OS Independent
Classifier: Programming Language :: Python :: 3.10
Classifier: Programming Language :: Python :: 3.11
Classifier: Programming Language :: Python :: 3.12
Classifier: Programming Language :: Python :: 3.13
Classifier: Typing :: Typed
Requires-Python: >=3.10
Requires-Dist: atomicwriter>=0.2.5
Requires-Dist: httpx>=0.27.2
Requires-Dist: msgspec>=0.19.0
Provides-Extra: cli
Requires-Dist: cyclopts>=3.9.0; extra == 'cli'
Requires-Dist: humanize>=4.12.2; extra == 'cli'
Requires-Dist: rich>=13.9.4; extra == 'cli'
Requires-Dist: torf>=4.2.7; extra == 'cli'
Provides-Extra: torrent
Requires-Dist: torf>=4.2.7; extra == 'torrent'
